ts_rnn/__init__.py
ts_rnn/config.py
ts_rnn/feature_selection.py
ts_rnn/logger.py
ts_rnn/model.py
ts_rnn/utils.py
ts_rnn-0.2.12.dist-info/METADATA
ts_rnn-0.2.12.dist-info/WHEEL
ts_rnn-0.2.12.dist-info/top_level.txt
ts_rnn-0.2.12.dist-info/RECORD
