Metadata-Version: 2.1
Name: ts-rnn
Version: 0.2.12
Summary: Package to forecast time series with recurrent neural network
Home-page: http://https://github.com/LevPerla/Time_Series_Prediction_RNN
Author: Lev Perla
Author-email: levperla@mail.ru
License: MIT
Keywords: rnn time-series keras data-science data-analysis python
Platform: UNKNOWN
Requires-Python: >= 3.7.3
Requires-Dist: pandas (>=1.1.5)
Requires-Dist: numpy (>=1.21.0)
Requires-Dist: tqdm (>=4.46.1)
Requires-Dist: tensorflow (>=2.1.0)
Requires-Dist: matplotlib (>=3.1.3)
Requires-Dist: keras-tuner (>=1.0.4)
